CHANGES.rst
LICENSE.txt
MANIFEST.in
README.rst
setup.cfg
setup.py
docs/Makefile
docs/conf.py
docs/configuration.rst
docs/index.rst
docs/supported_providers.rst
docs/_images/facebook/app-page.png
docs/_images/facebook/captcha-dialog.png
docs/_images/facebook/creation-dialog.png
docs/_images/google/api-access-home.png
docs/_images/google/api-access.png
docs/_images/google/branding-dialog.png
docs/_images/google/first-project.png
docs/_images/google/multiple-projects.png
docs/_images/google/project-home.png
docs/_images/google/project-name.png
docs/_images/google/redirect-uris.png
docs/_images/google/settings-dialog.png
docs/_images/liveconnect/app-summary-page.png
docs/_images/liveconnect/creation-dialog.png
pyramid_sna/__init__.py
pyramid_sna/compat.py
pyramid_sna/facebook.py
pyramid_sna/google.py
pyramid_sna/liveconnect.py
pyramid_sna/oauth2.py
pyramid_sna.egg-info/PKG-INFO
pyramid_sna.egg-info/SOURCES.txt
pyramid_sna.egg-info/dependency_links.txt
pyramid_sna.egg-info/not-zip-safe
pyramid_sna.egg-info/requires.txt
pyramid_sna.egg-info/top_level.txt
pyramid_sna/tests/__init__.py
pyramid_sna/tests/test_facebook.py
pyramid_sna/tests/test_google.py
pyramid_sna/tests/test_liveconnect.py
pyramid_sna/tests/test_oauth2.py