Metadata-Version: 1.1
Name: pyramid-sna
Version: 0.3.2
Summary: Pyramid Social Network Authentication
Home-page: https://github.com/lorenzogil/pyramid_sna
Author: Lorenzo Gil Sanchez
Author-email: lorenzo.gil.sanchez@gmail.com
License: UNKNOWN
Keywords: web pyramid pylons
Platform: UNKNOWN
Classifier: Development Status :: 3 - Alpha
Classifier: Framework :: Pyramid
Classifier: License :: OSI Approved :: BSD License
Classifier: Operating System :: OS Independent
Classifier: Programming Language :: Python
Classifier: Programming Language :: Python :: 2
Classifier: Programming Language :: Python :: 2.6
Classifier: Programming Language :: Python :: 2.7
Classifier: Programming Language :: Python :: 3
Classifier: Programming Language :: Python :: 3.2
Classifier: Programming Language :: Python :: 3.3
Classifier: Programming Language :: Python :: Implementation :: CPython
Classifier: Topic :: Internet :: WWW/HTTP
Classifier: Topic :: Internet :: WWW/HTTP :: WSGI :: Application
